bridge/.gitattributes
bridge/__init__.py
bridge/eeg/__init__.py
bridge/eeg/config.py
bridge/eeg/connector.py
bridge/eeg/brainaccess/__init__.py
bridge/eeg/brainaccess/cap_factory.py
bridge/eeg/brainaccess/config.py
bridge/eeg/brainaccess/device.py
bridge/eeg/brainaccess/typing.py
bridge/eeg/core/__init__.py
bridge/eeg/core/device.py
bridge/eeg/core/device_data.py
bridge/eeg/core/typing.py
bridge/server/__init__.py
bridge/server/cli.py
bridge/server/server.py
bridge/server/handlers/__init__.py
bridge/server/handlers/backend.py
bridge/server/handlers/frontend.py
neuron_bridge-0.2.0.dist-info/METADATA
neuron_bridge-0.2.0.dist-info/WHEEL
neuron_bridge-0.2.0.dist-info/entry_points.txt
neuron_bridge-0.2.0.dist-info/RECORD
