Metadata-Version: 2.4
Name: neuron-bridge
Version: 0.2.0
Summary: A versatile bridge application and SDK for connecting with EEG devices.
Project-URL: Homepage, https://github.com/KN-Neuron/Bridge
Project-URL: Issues, https://github.com/KN-Neuron/Bridge/issues
Author-email: mateusz-kow <kowalski.mateusz.1lo1@gmail.com>
Classifier: Development Status :: 4 - Beta
Classifier: Intended Audience :: Developers
Classifier: Intended Audience :: Science/Research
Classifier: Operating System :: OS Independent
Classifier: Programming Language :: Python :: 3
Classifier: Programming Language :: Python :: 3.11
Classifier: Topic :: Scientific/Engineering
Requires-Python: <3.12,>=3.11.0
Requires-Dist: numpy~=1.26.4
Provides-Extra: dev
Requires-Dist: black~=25.1.0; extra == 'dev'
Requires-Dist: hatchling~=1.27.0; extra == 'dev'
Requires-Dist: matplotlib~=3.10.6; extra == 'dev'
Requires-Dist: mne~=1.6.1; extra == 'dev'
Requires-Dist: mypy~=1.18.1; extra == 'dev'
Requires-Dist: pandas~=2.3.2; extra == 'dev'
Requires-Dist: pre-commit~=4.2.0; extra == 'dev'
Requires-Dist: pytest-asyncio~=1.2.0; extra == 'dev'
Requires-Dist: pytest-mock~=3.15.0; extra == 'dev'
Requires-Dist: pytest~=8.4.2; extra == 'dev'
Requires-Dist: ruff~=0.13.0; extra == 'dev'
Requires-Dist: twine~=6.2.0; extra == 'dev'
Requires-Dist: websockets~=12.0; extra == 'dev'
Provides-Extra: server
Requires-Dist: websockets~=12.0; extra == 'server'
